quanto/__init__.py
quanto/calibrate.py
quanto/quantize.py
quanto/serialization.py
quanto/library/README.md
quanto/library/__init__.py
quanto/library/ops.py
quanto/library/ext/README.md
quanto/library/ext/__init__.py
quanto/library/ext/cpp/README.md
quanto/library/ext/cpp/__init__.py
quanto/library/ext/cpp/mm.cpp
quanto/library/ext/cpp/mm.h
quanto/library/ext/cpp/pybind_module.cpp
quanto/library/ext/cpp/unpack.cpp
quanto/library/ext/cpp/unpack.h
quanto/library/ext/cuda/README.md
quanto/library/ext/cuda/__init__.py
quanto/library/ext/cuda/pybind_module.cpp
quanto/library/ext/cuda/unpack.cu
quanto/library/ext/cuda/unpack.h
quanto/library/ext/cuda/awq/dequantize.cuh
quanto/library/ext/cuda/awq/v2/gemm_cuda.cu
quanto/library/ext/cuda/awq/v2/gemm_cuda.h
quanto/library/ext/cuda/awq/v2/gemv_cuda.cu
quanto/library/ext/cuda/awq/v2/gemv_cuda.h
quanto/library/ext/cuda/awq/v2/semaphore.h
quanto/library/ext/mps/README.md
quanto/library/ext/mps/__init__.py
quanto/library/ext/mps/pybind_module.cpp
quanto/library/ext/mps/unpack.h
quanto/library/ext/mps/unpack.mm
quanto/library/python/README.md
quanto/library/python/__init__.py
quanto/library/python/mm.py
quanto/library/python/unpack.py
quanto/nn/__init__.py
quanto/nn/qconv2d.py
quanto/nn/qlayernorm.py
quanto/nn/qlinear.py
quanto/nn/qmodule.py
quanto/tensor/__init__.py
quanto/tensor/core.py
quanto/tensor/qactivation.py
quanto/tensor/qbytes.py
quanto/tensor/qbytes_ops.py
quanto/tensor/qtensor.py
quanto/tensor/qtensor_func.py
quanto/tensor/qtype.py
quanto/tensor/qweight.py
quanto/tensor/optimizers/__init__.py
quanto/tensor/optimizers/absmax_optimizer.py
quanto/tensor/optimizers/affine_optimizer.py
quanto/tensor/optimizers/max_optimizer.py
quanto/tensor/optimizers/optimizer.py
quanto/tensor/optimizers/symmetric_optimizer.py
quanto/tensor/qbits/__init__.py
quanto/tensor/qbits/group.py
quanto/tensor/qbits/packed.py
quanto/tensor/qbits/qbits.py
quanto/tensor/qbits/qbits_ops.py
quanto/tensor/qbits/awq/__init__.py
quanto-0.2.0.dist-info/LICENSE
quanto-0.2.0.dist-info/METADATA
quanto-0.2.0.dist-info/WHEEL
quanto-0.2.0.dist-info/top_level.txt
quanto-0.2.0.dist-info/RECORD
