Metadata-Version: 2.1
Name: quanto
Version: 0.2.0
Summary: A quantization toolkit for pytorch.
Home-page: https://github.com/huggingface/quanto
Author: David Corvoysier
Author-email: David Corvoysier <david@huggingface.co>
License: Apache-2.0
Project-URL: homepage, https://github.com/huggingface/quanto
Keywords: torch,quantization
Classifier: Development Status :: 2 - Pre-Alpha
Classifier: License :: OSI Approved :: Apache Software License
Classifier: Intended Audience :: Developers
Classifier: Intended Audience :: Education
Classifier: Intended Audience :: Science/Research
Classifier: Operating System :: OS Independent
Classifier: Programming Language :: Python :: 3.8
Classifier: Programming Language :: Python :: 3.9
Classifier: Programming Language :: Python :: 3.10
Classifier: Programming Language :: Python :: 3.11
Classifier: Topic :: Scientific/Engineering :: Artificial Intelligence
Requires-Python: >=3.8.0
License-File: LICENSE
Requires-Dist: torch >=2.2.0
Requires-Dist: ninja
Requires-Dist: numpy
Requires-Dist: safetensors
Provides-Extra: dev
Requires-Dist: pytest ; extra == 'dev'
Requires-Dist: ruff ; extra == 'dev'
Requires-Dist: black ; extra == 'dev'
Provides-Extra: examples
Requires-Dist: torchvision ; extra == 'examples'
Requires-Dist: transformers ==4.40.2 ; extra == 'examples'
Requires-Dist: datasets ; extra == 'examples'
